docusign_webforms/__init__.py
docusign_webforms/apis/__init__.py
docusign_webforms/apis/form_instance_management_api.py
docusign_webforms/apis/form_management_api.py
docusign_webforms/client/__init__.py
docusign_webforms/client/api_client.py
docusign_webforms/client/api_exception.py
docusign_webforms/client/api_response.py
docusign_webforms/client/configuration.py
docusign_webforms/client/auth/__init__.py
docusign_webforms/client/auth/oauth.py
docusign_webforms/models/__init__.py
docusign_webforms/models/account_id.py
docusign_webforms/models/assertion_id.py
docusign_webforms/models/authentication_instant.py
docusign_webforms/models/authentication_method.py
docusign_webforms/models/brand_id.py
docusign_webforms/models/client_user_id.py
docusign_webforms/models/component_key.py
docusign_webforms/models/count.py
docusign_webforms/models/create_instance_request_body.py
docusign_webforms/models/created_date_time.py
docusign_webforms/models/envelope_id.py
docusign_webforms/models/expiration_date_time.py
docusign_webforms/models/expiration_offset.py
docusign_webforms/models/form_sort_by.py
docusign_webforms/models/form_url.py
docusign_webforms/models/guid.py
docusign_webforms/models/http_error.py
docusign_webforms/models/http_success.py
docusign_webforms/models/instance_id.py
docusign_webforms/models/instance_source.py
docusign_webforms/models/instance_status.py
docusign_webforms/models/instance_token.py
docusign_webforms/models/is_private_access.py
docusign_webforms/models/is_published.py
docusign_webforms/models/is_standalone.py
docusign_webforms/models/last_modified_date_time.py
docusign_webforms/models/model_date_time.py
docusign_webforms/models/return_url.py
docusign_webforms/models/search_text.py
docusign_webforms/models/security_domain.py
docusign_webforms/models/source.py
docusign_webforms/models/start_position.py
docusign_webforms/models/tags.py
docusign_webforms/models/template_properties.py
docusign_webforms/models/token_expiration_date_time.py
docusign_webforms-2.0.0.dist-info/METADATA
docusign_webforms-2.0.0.dist-info/WHEEL
docusign_webforms-2.0.0.dist-info/top_level.txt
docusign_webforms-2.0.0.dist-info/RECORD
