Metadata-Version: 2.1
Name: docusign-webforms
Version: 2.0.0
Summary: Web Forms API version 1.1
Home-page: 
Author-email: devcenter@docusign.com
Keywords: Swagger,Web Forms API version 1.1
Requires-Dist: urllib3 (>=1.15)
Requires-Dist: six (>=1.8.0)
Requires-Dist: certifi (>=14.05.14)
Requires-Dist: python-dateutil (>=2.5.3)
Requires-Dist: setuptools (>=21.0.0)
Requires-Dist: PyJWT (>=2.0.0)
Requires-Dist: cryptography (>=2.5)
